simple_specification/__init__.py
simple_specification-0.3.dist-info/LICENSE.txt
simple_specification-0.3.dist-info/METADATA
simple_specification-0.3.dist-info/WHEEL
simple_specification-0.3.dist-info/top_level.txt
simple_specification-0.3.dist-info/RECORD
