Metadata-Version: 2.1
Name: simple-specification
Version: 0.3
Summary: A simple pythonic implementation of the Specification Pattern for Python 3.7 or higher.
Home-page: https://github.com/victor-o-silva/simple-specification
Author: Victor Oliveira da Silva
Author-email: victor_o_silva@hotmail.com
License: UNKNOWN
Download-URL: https://github.com/victor-o-silva/simple-specification/tarball/0.3
Platform: UNKNOWN
Classifier: License :: OSI Approved :: MIT License
Classifier: Programming Language :: Python :: 3.7
